vedbsearch/__init__.py
vedbsearch/client.py
vedbsearch-0.1.1.dist-info/licenses/LICENSE
vedbsearch-0.1.1.dist-info/METADATA
vedbsearch-0.1.1.dist-info/WHEEL
vedbsearch-0.1.1.dist-info/top_level.txt
vedbsearch-0.1.1.dist-info/RECORD
