Metadata-Version: 2.4
Name: vedbsearch
Version: 0.1.1
Summary: vedb-search client for accessing VeDB through LangChain VectorStores
Author-email: SiYi Yang <yangsiyi.1412ethan@bytedance.com>
License: MIT
Project-URL: Homepage, https://github.com/yangsiyi1412ethan/vedbsearch
Project-URL: Bug Tracker, https://github.com/yangsiyi1412ethan/vedbsearch/issues
Requires-Python: >=3.8
License-File: LICENSE
Requires-Dist: mysql-connector-python>=9.3.0
Dynamic: license-file
